{
    "os": "Linux-5.15.0-107-generic-x86_64-with-glibc2.29",
    "python": "3.8.10",
    "heartbeatAt": "2024-05-17T06:13:21.588919",
    "startedAt": "2024-05-17T06:13:20.328362",
    "docker": null,
    "cuda": null,
    "args": [],
    "state": "running",
    "program": "detect.py",
    "codePathLocal": "detect.py",
    "codePath": "coverage/Yolo/detect.py",
    "git": {
        "remote": null,
        "commit": null
    },
    "email": "leomagic170@gmail.com",
    "root": "/home/leo/mts/src",
    "host": "leo-System-Product-Name",
    "username": "leo",
    "executable": "/usr/bin/python3",
    "cpu_count": 24,
    "cpu_count_logical": 32,
    "cpu_freq": {
        "current": 2860.928125,
        "min": 800.0,
        "max": 4937.5
    },
    "cpu_freq_per_core": [
        {
            "current": 2162.896,
            "min": 800.0,
            "max": 5500.0
        },
        {
            "current": 2715.772,
            "min": 800.0,
            "max": 5500.0
        },
        {
            "current": 1778.309,
            "min": 800.0,
            "max": 5500.0
        },
        {
            "current": 1737.399,
            "min": 800.0,
            "max": 5500.0
        },
        {
            "current": 2085.26,
            "min": 800.0,
            "max": 5500.0
        },
        {
            "current": 2930.348,
            "min": 800.0,
            "max": 5500.0
        },
        {
            "current": 2164.639,
            "min": 800.0,
            "max": 5500.0
        },
        {
            "current": 2765.135,
            "min": 800.0,
            "max": 5500.0
        },
        {
            "current": 4690.946,
            "min": 800.0,
            "max": 5800.0
        },
        {
            "current": 1779.842,
            "min": 800.0,
            "max": 5800.0
        },
        {
            "current": 2525.467,
            "min": 800.0,
            "max": 5800.0
        },
        {
            "current": 2144.076,
            "min": 800.0,
            "max": 5800.0
        },
        {
            "current": 2343.776,
            "min": 800.0,
            "max": 5500.0
        },
        {
            "current": 1100.487,
            "min": 800.0,
            "max": 5500.0
        },
        {
            "current": 1849.488,
            "min": 800.0,
            "max": 5500.0
        },
        {
            "current": 1585.232,
            "min": 800.0,
            "max": 5500.0
        },
        {
            "current": 994.134,
            "min": 800.0,
            "max": 4300.0
        },
        {
            "current": 1548.683,
            "min": 800.0,
            "max": 4300.0
        },
        {
            "current": 1001.164,
            "min": 800.0,
            "max": 4300.0
        },
        {
            "current": 1783.444,
            "min": 800.0,
            "max": 4300.0
        },
        {
            "current": 2845.413,
            "min": 800.0,
            "max": 4300.0
        },
        {
            "current": 3078.535,
            "min": 800.0,
            "max": 4300.0
        },
        {
            "current": 2608.157,
            "min": 800.0,
            "max": 4300.0
        },
        {
            "current": 2550.785,
            "min": 800.0,
            "max": 4300.0
        },
        {
            "current": 912.318,
            "min": 800.0,
            "max": 4300.0
        },
        {
            "current": 799.185,
            "min": 800.0,
            "max": 4300.0
        },
        {
            "current": 3333.628,
            "min": 800.0,
            "max": 4300.0
        },
        {
            "current": 2842.015,
            "min": 800.0,
            "max": 4300.0
        },
        {
            "current": 1615.822,
            "min": 800.0,
            "max": 4300.0
        },
        {
            "current": 3282.726,
            "min": 800.0,
            "max": 4300.0
        },
        {
            "current": 1874.695,
            "min": 800.0,
            "max": 4300.0
        },
        {
            "current": 900.038,
            "min": 800.0,
            "max": 4300.0
        }
    ],
    "disk": {
        "/": {
            "total": 915.3223114013672,
            "used": 522.856014251709
        }
    },
    "gpu": "NVIDIA GeForce RTX 3070 Ti",
    "gpu_count": 1,
    "gpu_devices": [
        {
            "name": "NVIDIA GeForce RTX 3070 Ti",
            "memory_total": 8589934592
        }
    ],
    "memory": {
        "total": 62.50286102294922
    }
}
